aicp_auth/__init__.py
aicp_auth/client.py
aicp_auth/exceptions.py
aicp_auth/middleware.py
aicp_auth/types.py
aicp_auth_python-1.0.1.dist-info/licenses/LICENSE
aicp_auth_python-1.0.1.dist-info/METADATA
aicp_auth_python-1.0.1.dist-info/WHEEL
aicp_auth_python-1.0.1.dist-info/top_level.txt
aicp_auth_python-1.0.1.dist-info/RECORD
