Metadata-Version: 2.4
Name: aicp-auth-python
Version: 1.0.1
Summary: Biblioteca de autenticação e autorização para Keycloak com suporte a permissões contextuais - Python
Author-email: AI Cockpit Team <team@ai-cockpit.com>
License: MIT
Project-URL: Homepage, https://github.com/ai-cockpit/auth-lib
Project-URL: Documentation, https://github.com/ai-cockpit/auth-lib#readme
Project-URL: Repository, https://github.com/ai-cockpit/auth-lib.git
Project-URL: Issues, https://github.com/ai-cockpit/auth-lib/issues
Keywords: keycloak,authentication,authorization,rbac,permissions,jwt,oauth2,openid-connect,aicp
Classifier: Development Status :: 4 - Beta
Classifier: Intended Audience :: Developers
Classifier: License :: OSI Approved :: MIT License
Classifier: Operating System :: OS Independent
Classifier: Programming Language :: Python :: 3
Classifier: Programming Language :: Python :: 3.8
Classifier: Programming Language :: Python :: 3.9
Classifier: Programming Language :: Python :: 3.10
Classifier: Programming Language :: Python :: 3.11
Classifier: Programming Language :: Python :: 3.12
Classifier: Topic :: Software Development :: Libraries :: Python Modules
Classifier: Topic :: System :: Systems Administration :: Authentication/Directory
Requires-Python: >=3.8
License-File: LICENSE
Requires-Dist: requests>=2.25.0
Requires-Dist: PyJWT>=2.0.0
Requires-Dist: cryptography>=3.0.0
Requires-Dist: python-keycloak>=3.0.0
Provides-Extra: dev
Requires-Dist: pytest>=6.0.0; extra == "dev"
Requires-Dist: pytest-cov>=2.0.0; extra == "dev"
Requires-Dist: black>=21.0.0; extra == "dev"
Requires-Dist: flake8>=3.8.0; extra == "dev"
Requires-Dist: mypy>=0.800; extra == "dev"
Requires-Dist: pre-commit>=2.15.0; extra == "dev"
Provides-Extra: flask
Requires-Dist: flask>=2.0.0; extra == "flask"
Provides-Extra: fastapi
Requires-Dist: fastapi>=0.68.0; extra == "fastapi"
Requires-Dist: uvicorn>=0.15.0; extra == "fastapi"
Dynamic: license-file
Dynamic: requires-python
